easyf1/__init__.py
easyf1/api.py
easyf1/functions.py
easyf1/adapters/__init__.py
easyf1/adapters/livetimingf1_adapter.py
easyf1/adapters/realtime_client.py
easyf1/adapters/signalr_aio/__init__.py
easyf1/adapters/signalr_aio/_connection.py
easyf1/adapters/signalr_aio/events/__init__.py
easyf1/adapters/signalr_aio/events/_events.py
easyf1/adapters/signalr_aio/hubs/__init__.py
easyf1/adapters/signalr_aio/hubs/_hub.py
easyf1/adapters/signalr_aio/transports/__init__.py
easyf1/adapters/signalr_aio/transports/_exceptions.py
easyf1/adapters/signalr_aio/transports/_parameters.py
easyf1/adapters/signalr_aio/transports/_queue_events.py
easyf1/adapters/signalr_aio/transports/_transport.py
easyf1/data_processing/__init__.py
easyf1/data_processing/data_models.py
easyf1/data_processing/etl.py
easyf1/data_processing/old_etl.py
easyf1/models/__init__.py
easyf1/models/meeting.py
easyf1/models/season.py
easyf1/models/session.py
easyf1/utils/__init__.py
easyf1/utils/constants.py
easyf1/utils/exceptions.py
easyf1/utils/helper.py
easyf1/utils/logger.py
onef1-0.0.1.dist-info/LICENSE
onef1-0.0.1.dist-info/METADATA
onef1-0.0.1.dist-info/WHEEL
onef1-0.0.1.dist-info/top_level.txt
onef1-0.0.1.dist-info/RECORD
