Metadata-Version: 2.1
Name: onef1
Version: 0.0.1
Summary: A Python toolkit for seamless access to live and historical Formula 1 data.
Home-page: https://github.com/GoktugOcal/EasyF1
Author: Göktuğ Öcal
License: MIT
Project-URL: Bug Tracker, https://github.com/GoktugOcal/easyF1/issues
Project-URL: Documentation, https://github.com/GoktugOcal/easyF1#readme
Project-URL: Source Code, https://github.com/GoktugOcal/easyF1
Classifier: Programming Language :: Python :: 3
Classifier: License :: OSI Approved :: MIT License
Classifier: Operating System :: OS Independent
Requires-Python: >=3.7
License-File: LICENSE
Requires-Dist: pandas==2.2.3
Requires-Dist: python-dateutil==2.8.2
Requires-Dist: Requests==2.32.3
